blt_funcx_toolkit/__init__.py
blt_funcx_toolkit/blt_transfer.py
blt_funcx_toolkit/config.py
blt_funcx_toolkit/execution.py
blt_funcx_toolkit/fxsh.py
blt_funcx_toolkit/transfer.py
blt_funcx_toolkit/version.py
blt_funcx_toolkit-0.1.0.dist-info/METADATA
blt_funcx_toolkit-0.1.0.dist-info/WHEEL
blt_funcx_toolkit-0.1.0.dist-info/entry_points.txt
blt_funcx_toolkit-0.1.0.dist-info/top_level.txt
blt_funcx_toolkit-0.1.0.dist-info/RECORD
