Metadata-Version: 2.1
Name: blt-funcx-toolkit
Version: 0.1.0
Summary: BLT FuncX Toolkit: For easily accessing FuncX endpoints
Home-page: https://github.com/benhg/blt-funcx-toolkit
Author: Ben Glick
Author-email: glick@glick.cloud
License: Apache License, Version 2.0
Keywords: funcX,FaaS,Function Serving,BLT
Platform: UNKNOWN
Classifier: Development Status :: 3 - Alpha
Classifier: Intended Audience :: Science/Research
Classifier: License :: OSI Approved :: Apache Software License
Classifier: Natural Language :: English
Classifier: Operating System :: OS Independent
Classifier: Programming Language :: Python :: 3
Classifier: Topic :: Scientific/Engineering
Requires-Python: >=3.6.0
Requires-Dist: funcx
Requires-Dist: funcx-endpoint
Requires-Dist: pysftp
